message_local/ChannelProviderConstants.py
message_local/CompoundMessage.py
message_local/CompoundMessageVerification.py
message_local/GetTestIds.py
message_local/MessageChannels.py
message_local/MessageConstants.py
message_local/MessageImportance.py
message_local/MessageLocal.py
message_local/MessageTemplates.py
message_local/Recipient.py
message_local/SmsMessageLocal.py
message_local/__init__.py
message_local-0.0.186.dist-info/METADATA
message_local-0.0.186.dist-info/WHEEL
message_local-0.0.186.dist-info/top_level.txt
message_local-0.0.186.dist-info/RECORD
