Metadata-Version: 2.4
Name: message-local
Version: 0.0.186
Home-page: https://github.com/circles-zone/message-local-python-package
Author: Circles
Author-email: info@circlez.ai
Classifier: Programming Language :: Python :: 3
Classifier: License :: Other/Proprietary License
Classifier: Operating System :: OS Independent
Requires-Dist: item-local>=0.0.9
Requires-Dist: api-management-local>=0.0.73
Requires-Dist: language-remote>=0.0.20
Requires-Dist: variable-local>=0.0.95
Requires-Dist: logger-local>=0.0.135
Requires-Dist: database-mysql-local>=0.1.6
Requires-Dist: star-local>=0.0.16
Requires-Dist: profile-local>=0.0.65
Requires-Dist: phones-local>=0.0.18
Requires-Dist: criteria-local
Requires-Dist: user-external-local
Dynamic: author
Dynamic: author-email
Dynamic: classifier
Dynamic: description
Dynamic: description-content-type
Dynamic: home-page
Dynamic: requires-dist
